setup.py
ggl/__init__.py
ggl/ggl.py
ggl.egg-info/PKG-INFO
ggl.egg-info/SOURCES.txt
ggl.egg-info/dependency_links.txt
ggl.egg-info/entry_points.txt
ggl.egg-info/top_level.txt