Metadata-Version: 1.0
Name: ggl
Version: 1.0.4
Summary: Open default browser, and search for text stored in clipboard
Home-page: https://github.com/kagemiku/ggl
Author: kage
Author-email: kagemiku@gmail.com
License: MIT
Keywords: google search text clipboard
Platform: UNKNOWN
